Metadata-Version: 1.0
Name: GardanLess
Version: 0.1
Summary: A unique creature
Home-page: UNKNOWN
Author: Sudhanshu Kumar
Author-email: UNKNOWN
License: UNKNOWN
Platform: UNKNOWN
